django_mpdcontroller-0.1.dist-info/DESCRIPTION.rst
django_mpdcontroller-0.1.dist-info/METADATA
django_mpdcontroller-0.1.dist-info/RECORD
django_mpdcontroller-0.1.dist-info/WHEEL
django_mpdcontroller-0.1.dist-info/metadata.json
django_mpdcontroller-0.1.dist-info/top_level.txt
mpdcontroller/__init__.py
mpdcontroller/admin.py
mpdcontroller/apps.py
mpdcontroller/models.py
mpdcontroller/tests.py
mpdcontroller/urls.py
mpdcontroller/views.py
mpdcontroller/migrations/__init__.py
