Metadata-Version: 2.0
Name: django-mpdcontroller
Version: 0.1
Summary: A web interface to command the music player daemon service (mpd).
Home-page: https://github.com/Sebatyne/django-feed-manager
Author: Nicolas Wavrant
Author-email: nicolas.wavrant@gmail.com
License: BSD
Keywords: django interface mpd client
Platform: UNKNOWN
Classifier: Environment :: Web Environment
Classifier: Framework :: Django
Classifier: Development Status :: 4 - Beta
Classifier: Topic :: Utilities
Classifier: License :: OSI Approved :: BSD License
Classifier: Operating System :: OS Independent
Classifier: Programming Language :: Python
Classifier: Programming Language :: Python :: 3
Classifier: Topic :: Internet :: WWW/HTTP
